bpy/__init__.so
bpy/2.79/scripts/addons/add_curve_ivygen.py
bpy/2.79/scripts/addons/animation_add_corrective_shape_key.py
bpy/2.79/scripts/addons/animation_animall.py
bpy/2.79/scripts/addons/bone_selection_sets.py
bpy/2.79/scripts/addons/camera_dolly_crane_rigs.py
bpy/2.79/scripts/addons/camera_turnaround.py
bpy/2.79/scripts/addons/curve_simplify.py
bpy/2.79/scripts/addons/development_api_navigator.py
bpy/2.79/scripts/addons/development_edit_operator.py
bpy/2.79/scripts/addons/development_icon_get.py
bpy/2.79/scripts/addons/development_iskeyfree.py
bpy/2.79/scripts/addons/development_ui_classes.py
bpy/2.79/scripts/addons/game_engine_publishing.py
bpy/2.79/scripts/addons/game_engine_save_as_runtime.py
bpy/2.79/scripts/addons/io_anim_camera.py
bpy/2.79/scripts/addons/io_export_after_effects.py
bpy/2.79/scripts/addons/io_export_paper_model.py
bpy/2.79/scripts/addons/io_export_pc2.py
bpy/2.79/scripts/addons/io_export_unreal_psk_psa.py
bpy/2.79/scripts/addons/io_import_gimp_image_to_scene.py
bpy/2.79/scripts/addons/io_import_images_as_planes.py
bpy/2.79/scripts/addons/io_import_scene_lwo.py
bpy/2.79/scripts/addons/io_import_scene_unreal_psa_psk.py
bpy/2.79/scripts/addons/lighting_dynamic_sky.py
bpy/2.79/scripts/addons/mesh_auto_mirror.py
bpy/2.79/scripts/addons/mesh_bsurfaces.py
bpy/2.79/scripts/addons/mesh_carver.py
bpy/2.79/scripts/addons/mesh_custom_normals_tools.py
bpy/2.79/scripts/addons/mesh_f2.py
bpy/2.79/scripts/addons/mesh_looptools.py
bpy/2.79/scripts/addons/mesh_relax.py
bpy/2.79/scripts/addons/mesh_snap_utilities_line.py
bpy/2.79/scripts/addons/node_wrangler.py
bpy/2.79/scripts/addons/object_animrenderbake.py
bpy/2.79/scripts/addons/object_boolean_tools.py
bpy/2.79/scripts/addons/object_cloud_gen.py
bpy/2.79/scripts/addons/object_edit_linked.py
bpy/2.79/scripts/addons/object_grease_scatter.py
bpy/2.79/scripts/addons/object_skinify.py
bpy/2.79/scripts/addons/paint_palette.py
bpy_2.79-1.0.0.dist-info/DESCRIPTION.rst
bpy_2.79-1.0.0.dist-info/METADATA
bpy_2.79-1.0.0.dist-info/RECORD
bpy_2.79-1.0.0.dist-info/WHEEL
bpy_2.79-1.0.0.dist-info/metadata.json
bpy_2.79-1.0.0.dist-info/top_level.txt
