Metadata-Version: 2.0
Name: bpy-2.79
Version: 1.0.0
Summary: Blender-as-a-python module for ubuntu 18.04, blender version 2.79
Home-page: UNKNOWN
Author: Shyamant Achar
Author-email: UNKNOWN
License: UNKNOWN
Platform: x86-64
